src/design/display7.sv
module display7 (
    input  logic [3:0] palabra,
    output logic [6:0] seg
);
    always_comb begin
        case (palabra)
            4'd0: seg = 7'b0111111;
            4'd1: seg = 7'b0000110;
            4'd2: seg = 7'b1011011;
            4'd3: seg = 7'b1001111;
            4'd4: seg = 7'b1100110;
            4'd5: seg = 7'b1101101;
            4'd6: seg = 7'b1111101;
            4'd7: seg = 7'b0000111;
            4'd8: seg = 7'b1111111;
            4'd9: seg = 7'b1101111;
            4'd10: seg = 7'b1110111;
            4'd11: seg = 7'b1111100;
            4'd12: seg = 7'b1111001;
            4'd13: seg = 7'b1011110;
            4'd14: seg = 7'b1111001;
            4'd15: seg = 7'b1110001;
            default: seg = 7'b0000000; // Off for invalid input
        endcase
    end
endmodule

src/sim/display7_tb.sv
`timescale 1ns/1ns

module display7_tb;

    reg [3:0] p;
    wire [6:0] seg;

    display7 dut (
        .palabra(p),
        .seg(seg)
    );

// Generación de estímulos
    initial begin
        $display("-------|---------|--------");
        $display("Tiempo | Entrada | Salida ");
        $display("-------|---------|--------");

        $monitor("Tiempo = %t, Entrada = %b, Salida = %b", $time , p, seg);
        
        p = 4'b0000; #10; // Caso 0
        p = 4'b0001; #10; // Caso 1
        p = 4'b0010; #10; // Caso 2
        p = 4'b0011; #10; // Caso 3
        p = 4'b0100; #10; // Caso 4
        p = 4'b0101; #10; // Caso 5
        p = 4'b0110; #10; // Caso 6
        p = 4'b0111; #10; // Caso 7
        p = 4'b1000; #10; // Caso 8
        p = 4'b1001; #10; // Caso 9
        p = 4'b1010; #10; // Caso A
        p = 4'b1011; #10; // Caso B
        p = 4'b1100; #10; // Caso C
        p = 4'b1101; #10; // Caso D
        p = 4'b1110; #10; // Caso E
        p = 4'b1111; #10; // Caso F

    end

     initial begin
        $dumpfile("display7_tb.vcd");
        $dumpvars(0, display7_tb);
    end
endmodule

src/build/display7_tb.vcd
$date
	Tue Sep 16 18:04:04 2025
$end
$version
	Icarus Verilog
$end
$timescale
	1ns
$end
$scope module display7_tb $end
$var wire 7 ! seg [6:0] $end
$var reg 4 " p [3:0] $end
$scope module dut $end
$var wire 4 # palabra [3:0] $end
$var reg 7 $ seg [6:0] $end
$upscope $end
$upscope $end
$enddefinitions $end
$comment Show the parameter values. $end
$dumpall
$end
#0
$dumpvars
b1000000 $
b0 #
b0 "
b1000000 !
$end
#10
b1111001 !
b1111001 $
b1 "
b1 #
#20
b100100 !
b100100 $
b10 "
b10 #
#30
b110000 !
b110000 $
b11 "
b11 #
#40
b11001 !
b11001 $
b100 "
b100 #
#50
b10010 !
b10010 $
b101 "
b101 #
#60
b10 !
b10 $
b110 "
b110 #
#70
b1111000 !
b1111000 $
b111 "
b111 #
#80
b0 !
b0 $
b1000 "
b1000 #
#90
b10000 !
b10000 $
b1001 "
b1001 #
#100
b1000 !
b1000 $
b1010 "
b1010 #
#110
b11 !
b11 $
b1011 "
b1011 #
#120
b110 !
b110 $
b1100 "
b1100 #
#130
b100001 !
b100001 $
b1101 "
b1101 #
#140
b110 !
b110 $
b1110 "
b1110 #
#150
b1110 !
b1110 $
b1111 "
b1111 #
